.hgignore
.hgtags
README.txt
setup.py
docs/HISTORY.txt
src/bethel/__init__.py
src/bethel.clustermgmt.egg-info/PKG-INFO
src/bethel.clustermgmt.egg-info/SOURCES.txt
src/bethel.clustermgmt.egg-info/dependency_links.txt
src/bethel.clustermgmt.egg-info/namespace_packages.txt
src/bethel.clustermgmt.egg-info/not-zip-safe
src/bethel.clustermgmt.egg-info/requires.txt
src/bethel.clustermgmt.egg-info/top_level.txt
src/bethel/clustermgmt/__init__.py
src/bethel/clustermgmt/configure.zcml
src/bethel/clustermgmt/health.py
src/bethel/clustermgmt/health.pyc
src/bethel/clustermgmt/healthReporterAdd.zpt
src/bethel/clustermgmt/healthreporter.png
src/bethel/clustermgmt/interfaces.py
src/bethel/clustermgmt/rest.py
src/bethel/clustermgmt/tests/HealthTestCase.py
src/bethel/clustermgmt/tests/__init__.py
src/bethel/clustermgmt/tests/layer.py
src/bethel/clustermgmt/tests/test_zmi.py