Metadata-Version: 1.0
Name: bethel.clustermgmt
Version: 1.0
Summary: Zope Cluster Management facilities
Home-page: http://pypi.python.org/pypi/bethel.clustermgmt
Author: Andy Altepeter
Author-email: aaltepet@bethel.edu
License: GPL
Keywords: python zope infrae varnish fabric
Platform: UNKNOWN
Classifier: Programming Language :: Python
Classifier: Development Status :: 5 - Production/Stable
Classifier: Environment :: Web Environment
Classifier: Framework :: Zope2
Classifier: Intended Audience :: Developers
Classifier: Intended Audience :: System Administrators
Classifier: License :: OSI Approved :: GNU General Public License (GPL)
Classifier: Topic :: Internet :: Proxy Servers
Classifier: Topic :: Internet :: WWW/HTTP :: Site Management
Classifier: Topic :: System :: Monitoring
